txtpy/__init__.py
txtpy/app.py
txtpy/clean.py
txtpy/fabric.py
txtpy/lib.py
txtpy/parameters.py
txtpy/advanced/__init__.py
txtpy/advanced/app.py
txtpy/advanced/condense.py
txtpy/advanced/data.py
txtpy/advanced/display.py
txtpy/advanced/find.py
txtpy/advanced/helpers.py
txtpy/advanced/highlight.py
txtpy/advanced/links.py
txtpy/advanced/options.py
txtpy/advanced/render.py
txtpy/advanced/repo.py
txtpy/advanced/search.py
txtpy/advanced/sections.py
txtpy/advanced/settings.py
txtpy/advanced/tables.py
txtpy/advanced/text.py
txtpy/advanced/unravel.py
txtpy/advanced/wrap.py
txtpy/advanced/zipdata.py
txtpy/compose/__init__.py
txtpy/compose/combine.py
txtpy/compose/modify.py
txtpy/compose/nodemaps.py
txtpy/convert/__init__.py
txtpy/convert/mql.py
txtpy/convert/recorder.py
txtpy/convert/tf.py
txtpy/convert/walker.py
txtpy/core/__init__.py
txtpy/core/api.py
txtpy/core/computed.py
txtpy/core/data.py
txtpy/core/edgefeature.py
txtpy/core/helpers.py
txtpy/core/locality.py
txtpy/core/nodefeature.py
txtpy/core/nodes.py
txtpy/core/oslotsfeature.py
txtpy/core/otypefeature.py
txtpy/core/prepare.py
txtpy/core/text.py
txtpy/core/timestamp.py
txtpy/search/__init__.py
txtpy/search/graph.py
txtpy/search/relations.py
txtpy/search/search.py
txtpy/search/searchexe.py
txtpy/search/semantics.py
txtpy/search/spin.py
txtpy/search/stitch.py
txtpy/search/syntax.py
txtpy/writing/__init__.py
txtpy/writing/transcription.py
txtpy-1.0.0.dist-info/LICENSE
txtpy-1.0.0.dist-info/METADATA
txtpy-1.0.0.dist-info/WHEEL
txtpy-1.0.0.dist-info/top_level.txt
txtpy-1.0.0.dist-info/RECORD
