Metadata-Version: 2.1
Name: txtpy
Version: 1.0.0
Summary: Processor Text Fabric Data
Home-page: https://github.com/annotation/txtpy
Author: Dirk Roorda
Author-email: dirk.roorda@dans.knaw.nl
License: UNKNOWN
Keywords: text,linguistics,database,graph,hebrew,bible,peshitta,quran,cuneiform,uruk,greek,syriac,akkadian,babylonian
Platform: UNKNOWN
Classifier: Development Status :: 4 - Beta
Classifier: Environment :: Other Environment
Classifier: Framework :: Jupyter
Classifier: Intended Audience :: Developers
Classifier: Intended Audience :: Education
Classifier: Intended Audience :: Religion
Classifier: Intended Audience :: Science/Research
Classifier: License :: OSI Approved :: MIT License
Classifier: Natural Language :: English
Classifier: Natural Language :: Hebrew
Classifier: Natural Language :: Greek
Classifier: Operating System :: MacOS :: MacOS X
Classifier: Operating System :: Microsoft :: Windows :: Windows 10
Classifier: Operating System :: POSIX :: Linux
Classifier: Programming Language :: Python :: 3 :: Only
Classifier: Programming Language :: Python :: Implementation :: CPython
Classifier: Programming Language :: JavaScript
Classifier: Topic :: Religion
Classifier: Topic :: Scientific/Engineering :: Information Analysis
Classifier: Topic :: Sociology :: History
Classifier: Topic :: Text Processing :: Filters
Classifier: Topic :: Text Processing :: Linguistic
Classifier: Topic :: Text Processing :: Markup
Requires-Python: >=3.7.0
Requires-Dist: markdown
Requires-Dist: ipython
Requires-Dist: requests
Requires-Dist: pygithub (>=1.47)
Requires-Dist: pyyaml (>=5.3)
